{
  "month": "SEPTEMBER",
  "prayer_times": [
    {
      "date": 1,
      "fajr": "04:36",
      "shurooq": "06:15",
      "dhuhr": "13:11",
      "asr": "16:49",
      "maghrib": "19:58",
      "isha": "21:33"
    },
    {
      "date": 2,
      "fajr": "04:38",
      "shurooq": "06:17",
      "dhuhr": "13:10",
      "asr": "16:47",
      "maghrib": "19:56",
      "isha": "21:31"
    },
    {
      "date": 3,
      "fajr": "04:40",
      "shurooq": "06:19",
      "dhuhr": "13:10",
      "asr": "16:46",
      "maghrib": "19:53",
      "isha": "21:28"
    },
    {
      "date": 4,
      "fajr": "04:42",
      "shurooq": "06:21",
      "dhuhr": "13:10",
      "asr": "16:44",
      "maghrib": "19:51",
      "isha": "21:26"
    },
    {
      "date": 5,
      "fajr": "04:44",
      "shurooq": "06:22",
      "dhuhr": "13:09",
      "asr": "16:43",
      "maghrib": "19:48",
      "isha": "21:23"
    },
    {
      "date": 6,
      "fajr": "04:46",
      "shurooq": "06:24",
      "dhuhr": "13:09",
      "asr": "16:41",
      "maghrib": "19:46",
      "isha": "21:21"
    },
    {
      "date": 7,
      "fajr": "04:48",
      "shurooq": "06:26",
      "dhuhr": "13:09",
      "asr": "16:39",
      "maghrib": "19:44",
      "isha": "21:18"
    },
    {
      "date": 8,
      "fajr": "04:50",
      "shurooq": "06:27",
      "dhuhr": "13:08",
      "asr": "16:38",
      "maghrib": "19:41",
      "isha": "21:15"
    },
    {
      "date": 9,
      "fajr": "04:52",
      "shurooq": "06:29",
      "dhuhr": "13:08",
      "asr": "16:36",
      "maghrib": "19:39",
      "isha": "21:13"
    },
    {
      "date": 10,
      "fajr": "04:54",
      "shurooq": "06:31",
      "dhuhr": "13:08",
      "asr": "16:35",
      "maghrib": "19:36",
      "isha": "21:10"
    },
    {
      "date": 11,
      "fajr": "04:56",
      "shurooq": "06:33",
      "dhuhr": "13:07",
      "asr": "16:33",
      "maghrib": "19:34",
      "isha": "21:20"
    },
    {
      "date": 12,
      "fajr": "04:58",
      "shurooq": "06:34",
      "dhuhr": "13:07",
      "asr": "16:31",
      "maghrib": "19:31",
      "isha": "21:05"
    },
    {
      "date": 13,
      "fajr": "05:00",
      "shurooq": "06:36",
      "dhuhr": "13:07",
      "asr": "16:30",
      "maghrib": "19:29",
      "isha": "21:02"
    },
    {
      "date": 14,
      "fajr": "05:02",
      "shurooq": "06:38",
      "dhuhr": "13:06",
      "asr": "16:28",
      "maghrib": "19:27",
      "isha": "21:00"
    },
    {
      "date": 15,
      "fajr": "05:04",
      "shurooq": "06:40",
      "dhuhr": "13:06",
      "asr": "16:26",
      "maghrib": "19:24",
      "isha": "20:57"
    },
    {
      "date": 16,
      "fajr": "05:06",
      "shurooq": "06:41",
      "dhuhr": "13:06",
      "asr": "16:25",
      "maghrib": "19:22",
      "isha": "20:54"
    },
    {
      "date": 17,
      "fajr": "05:08",
      "shurooq": "06:43",
      "dhuhr": "13:05",
      "asr": "16:23",
      "maghrib": "19:19",
      "isha": "20:52"
    },
    {
      "date": 18,
      "fajr": "05:10",
      "shurooq": "06:45",
      "dhuhr": "13:05",
      "asr": "16:21",
      "maghrib": "19:17",
      "isha": "20:49"
    },
    {
      "date": 19,
      "fajr": "05:12",
      "shurooq": "06:47",
      "dhuhr": "13:04",
      "asr": "16:20",
      "maghrib": "19:14",
      "isha": "20:47"
    },
    {
      "date": 20,
      "fajr": "05:14",
      "shurooq": "06:48",
      "dhuhr": "13:04",
      "asr": "16:18",
      "maghrib": "19:12",
      "isha": "20:44"
    },
    {
      "date": 21,
      "fajr": "05:16",
      "shurooq": "06:50",
      "dhuhr": "13:04",
      "asr": "16:16",
      "maghrib": "19:09",
      "isha": "20:42"
    },
    {
      "date": 22,
      "fajr": "05:12",
      "shurooq": "06:51",
      "dhuhr": "13:03",
      "asr": "16:14",
      "maghrib": "19:07",
      "isha": "20:39"
    },
    {
      "date": 23,
      "fajr": "05:20",
      "shurooq": "06:53",
      "dhuhr": "13:03",
      "asr": "16:13",
      "maghrib": "19:05",
      "isha": "20:37"
    },
    {
      "date": 24,
      "fajr": "05:21",
      "shurooq": "06:55",
      "dhuhr": "13:03",
      "asr": "16:11",
      "maghrib": "19:02",
      "isha": "20:35"
    },
    {
      "date": 25,
      "fajr": "05:23",
      "shurooq": "06:57",
      "dhuhr": "13:02",
      "asr": "16:09",
      "maghrib": "19:00",
      "isha": "20:32"
    },
    {
      "date": 26,
      "fajr": "05:24",
      "shurooq": "06:59",
      "dhuhr": "13:02",
      "asr": "16:07",
      "maghrib": "18:57",
      "isha": "20:30"
    },
    {
      "date": 27,
      "fajr": "05:26",
      "shurooq": "07:00",
      "dhuhr": "13:02",
      "asr": "16:05",
      "maghrib": "18:55",
      "isha": "20:27"
    },
    {
      "date": 28,
      "fajr": "05:28",
      "shurooq": "07:02",
      "dhuhr": "13:01",
      "asr": "16:04",
      "maghrib": "18:52",
      "isha": "20:25"
    },
    {
      "date": 29,
      "fajr": "05:29",
      "shurooq": "07:04",
      "dhuhr": "13:01",
      "asr": "16:02",
      "maghrib": "18:50",
      "isha": "20:23"
    },
    {
      "date": 30,
      "fajr": "05:26",
      "shurooq": "07:04",
      "dhuhr": "13:01",
      "asr": "16:00",
      "maghrib": "18:47",
      "isha": "20:20"
    }
  ],
  "iqamah_times": [
    {
      "date_range": "1",
      "fajr": "05:15",
      "dhuhr": "13:30",
      "asr": "17:15",
      "maghrib": "20:03",
      "isha": "21:33"
    },
    {
      "date_range": "2",
      "fajr": "05:15",
      "dhuhr": "13:30",
      "asr": "17:15",
      "maghrib": "20:01",
      "isha": "21:31"
    },
    {
      "date_range": "3",
      "fajr": "05:15",
      "dhuhr": "13:30",
      "asr": "17:15",
      "maghrib": "19:58",
      "isha": "21:28"
    },
    {
      "date_range": "4",
      "fajr": "05:15",
      "dhuhr": "13:30",
      "asr": "17:15",
      "maghrib": "19:56",
      "isha": "21:26"
    },
    {
      "date_range": "5",
      "fajr": "05:15",
      "dhuhr": "13:30",
      "asr": "17:15",
      "maghrib": "19:53",
      "isha": "21:23"
    },
    {
      "date_range": "6",
      "fajr": "05:15",
      "dhuhr": "13:30",
      "asr": "17:15",
      "maghrib": "19:51",
      "isha": "21:21"
    },
    {
      "date_range": "7",
      "fajr": "05:30",
      "dhuhr": "13:30",
      "asr": "17:15",
      "maghrib": "19:49",
      "isha": "21:18"
    },
    {
      "date_range": "8",
      "fajr": "05:30",
      "dhuhr": "13:30",
      "asr": "17:15",
      "maghrib": "19:46",
      "isha": "21:15"
    },
    {
      "date_range": "9",
      "fajr": "05:30",
      "dhuhr": "13:30",
      "asr": "17:15",
      "maghrib": "19:44",
      "isha": "21:13"
    },
    {
      "date_range": "10",
      "fajr": "05:30",
      "dhuhr": "13:30",
      "asr": "17:15",
      "maghrib": "19:41",
      "isha": "21:10"
    },
    {
      "date_range": "11",
      "fajr": "05:30",
      "dhuhr": "13:30",
      "asr": "17:15",
      "maghrib": "19:39",
      "isha": "21:20"
    },
    {
      "date_range": "12",
      "fajr": "05:30",
      "dhuhr": "13:30",
      "asr": "17:15",
      "maghrib": "19:36",
      "isha": "21:05"
    },
    {
      "date_range": "13",
      "fajr": "05:30",
      "dhuhr": "13:30",
      "asr": "17:15",
      "maghrib": "19:34",
      "isha": "21:02"
    },
    {
      "date_range": "14",
      "fajr": "05:45",
      "dhuhr": "13:30",
      "asr": "17:00",
      "maghrib": "19:32",
      "isha": "21:00"
    },
    {
      "date_range": "15",
      "fajr": "05:45",
      "dhuhr": "13:30",
      "asr": "17:00",
      "maghrib": "19:29",
      "isha": "20:57"
    },
    {
      "date_range": "16",
      "fajr": "05:45",
      "dhuhr": "13:30",
      "asr": "17:00",
      "maghrib": "19:27",
      "isha": "20:54"
    },
    {
      "date_range": "17",
      "fajr": "05:45",
      "dhuhr": "13:30",
      "asr": "17:00",
      "maghrib": "19:24",
      "isha": "20:52"
    },
    {
      "date_range": "18",
      "fajr": "05:45",
      "dhuhr": "13:30",
      "asr": "17:00",
      "maghrib": "19:22",
      "isha": "20:49"
    },
    {
      "date_range": "19",
      "fajr": "05:45",
      "dhuhr": "13:30",
      "asr": "17:00",
      "maghrib": "19:19",
      "isha": "20:47"
    },
    {
      "date_range": "20",
      "fajr": "05:45",
      "dhuhr": "13:30",
      "asr": "17:00",
      "maghrib": "19:17",
      "isha": "20:44"
    },
    {
      "date_range": "21",
      "fajr": "06:00",
      "dhuhr": "13:30",
      "asr": "17:00",
      "maghrib": "19:14",
      "isha": "20:42"
    },
    {
      "date_range": "22",
      "fajr": "05:45",
      "dhuhr": "13:30",
      "asr": "16:45",
      "maghrib": "19:12",
      "isha": "20:39"
    },
    {
      "date_range": "23",
      "fajr": "06:00",
      "dhuhr": "13:30",
      "asr": "16:45",
      "maghrib": "19:10",
      "isha": "20:37"
    },
    {
      "date_range": "24",
      "fajr": "06:00",
      "dhuhr": "13:30",
      "asr": "16:45",
      "maghrib": "19:07",
      "isha": "20:35"
    },
    {
      "date_range": "25",
      "fajr": "06:00",
      "dhuhr": "13:30",
      "asr": "16:45",
      "maghrib": "19:05",
      "isha": "20:32"
    },
    {
      "date_range": "26",
      "fajr": "06:00",
      "dhuhr": "13:30",
      "asr": "16:45",
      "maghrib": "19:02",
      "isha": "20:30"
    },
    {
      "date_range": "27",
      "fajr": "06:00",
      "dhuhr": "13:30",
      "asr": "16:45",
      "maghrib": "19:00",
      "isha": "20:27"
    },
    {
      "date_range": "28",
      "fajr": "06:00",
      "dhuhr": "13:30",
      "asr": "16:45",
      "maghrib": "18:57",
      "isha": "20:25"
    },
    {
      "date_range": "29",
      "fajr": "06:00",
      "dhuhr": "13:30",
      "asr": "16:45",
      "maghrib": "18:55",
      "isha": "20:23"
    },
    {
      "date_range": "30",
      "fajr": "06:00",
      "dhuhr": "13:30",
      "asr": "16:45",
      "maghrib": "18:52",
      "isha": "20:20"
    }
  ],
  "jummah_iqamah": "12:15"
}
